KabirTiwariTestPackage/__init__.py
KabirTiwariTestPackage/module.py
kabirtiwaritestpackage-0.1.2.dist-info/licenses/LICENSE
kabirtiwaritestpackage-0.1.2.dist-info/METADATA
kabirtiwaritestpackage-0.1.2.dist-info/WHEEL
kabirtiwaritestpackage-0.1.2.dist-info/top_level.txt
kabirtiwaritestpackage-0.1.2.dist-info/RECORD
