Metadata-Version: 2.4
Name: KabirTiwariTestPackage
Version: 0.1.2
Summary: Simple Python Wrapper for the PokeAPI
Home-page: 
Author: Kabir Tiwari
Author-email: kabir.tiwari@outlook.com
License: MIT
Classifier: Programming Language :: Python :: 3
Classifier: License :: OSI Approved :: MIT License
Classifier: Operating System :: OS Independent
Requires-Python: >=3.7
License-File: LICENSE
Dynamic: license-file
